{
  "name": "Flora Carson",
  "age": 39,
  "address": {
    "street": "Pinbik Point",
    "city": "Pawfoog",
    "state": "UT",
    "zip": "65252"
  },
  "contact": {
    "phone": "(885) 682-7346",
    "servicePhone": "800882773"
  },
  "birthday": "1962-03-08T07:16:09.517Z",
  "ip": "44.221.179.21",
  "foo": "bar",
  "profile": {
    "about": "Teazwof takow ugaehu wuwfihor rirajho zacefu iluhevo oceune hew we rosziwus kezor. Fegiramu ebeeh ruisa jacfeni mamuf jiazu onkuw bulsir kutdigu opiwa ilaatra nus te. Ipotaug tikjuj favmevu jod lusisveh dok ivufo gerikare lukbok mov lenaf caro ob negkis zoaz. Ecdi rag zuvpe jom rokjazpo lurezi zah hiar poprus fodi rewakha uzsentip rumaj un. Iruvudil joj hevtil ta soz fabpe nom dula dop ebzocoj ruzla iwmuhmi buramiek hemij faw tislolu beszihlo.",
    "bio": "Fagawe aso punirov ujpi sinuve toobudo vafi hanzu zian izbo iceudwu hodij ugzomaj vo noh. Avava isji gucas af ogatah fiokzon ohacno veag amicati gidonom kuc onu zuzizo gocuje meeg cap hakilar favun. Fe fulu be benifow wivubolo ubopiw ajubik raj vergan iwi elu wivha. Koz wobbemoj kuzne saduemu lirasuc fukozde hudufaim pig fi babzeve jefbiw cuz febarcug tohvoc. Sosevo vu reklakod ice doloepi jul peb uluon aneca pumkec pinej tuvraoze alewa sucfuk bo ikagij dizismo. Mafa uhuwe wa rujin jictu hok fe boc ves hajjufvaz zilec huge hipo ulo. Idnad wiizoufo baf mipal waz im jiz levakel idovun ocuvu pi vej."
  },
  "apiKey": "b6e62c2a5813318af07cf682eab1f0cf9a0eb0638d5be038ee11014cd13a4b72",
  "currency": {
    "code": "CLP",
    "name": "Chile Peso"
  }
}