{
  "name": "Beatrice Abbott",
  "age": 48,
  "address": {
    "street": "Ince Parkway",
    "city": "Wizirzuk",
    "state": "MS",
    "zip": "06136"
  },
  "contact": {
    "phone": "(951) 941-9940",
    "servicePhone": "800117585"
  },
  "birthday": "1965-10-27T01:01:06.473Z",
  "ip": "12.227.48.102",
  "foo": "bar",
  "profile": {
    "about": "Lim ulpi gaihali olaludmuz pelfaja ic huim irju wudiguh um fawmukfaf kif. Dojuta ken sutde iboho utpewa uwa go olo ho vovresi cuzvis zu susza licub rifa. Ripopi lo sit donroznep suup tej oc eb casis muehidug otezok gecnupu ficugin zoghiz ewza jojepbo mijso feme. Rufni gogmaod ciel vokbe ajure atejnu fa meku zilejguz miwwedjer dogem duklathuf basni ib. Vosas di gu firid eg sabu upu ab havzu lizdo afowubi altetfon ca itewa sadaf bepgac fegjopar wioro. Pubepuire jufab caso vaz coval duhhu holdahla acwabaf omeviad jo imuas epcuupu.",
    "bio": "Wouc refpu febviste mo lolutev fiz ija ipovike fuw ciodsug mozjad notubpul sopav wojcuguc aloiwabo juvonzad opecojim. Kiwo ko ti tabup hozupjoc oni tuveh keicko ufona epluf disetaz kuwa daci fin lo. Aw ozfejwin tuj pukte dom vit ler jezfuna ce sen saom safmoab geriza. Men gewwolmeg lihogi pakvofaz hoheriko for iwiih ka ce atade mit pi lucfize gicjerzev jezingud azifev sosto epija. Mes cutuz arputase nondu vovsubso rezlogow hawehlu ofavi kok mo si otairiho useceded pokihi biovpav woda jeti sov."
  },
  "apiKey": "6045cf31505af968b92466436844d74bfb526fca715a72fcf1f39033d7d5c12e",
  "currency": {
    "code": "KWD",
    "name": "Kuwait Dinar"
  }
}